tf_bodypix/__init__.py
tf_bodypix/__main__.py
tf_bodypix/api.py
tf_bodypix/cli.py
tf_bodypix/download.py
tf_bodypix/draw.py
tf_bodypix/model.py
tf_bodypix/sink.py
tf_bodypix/source.py
tf_bodypix/tflite.py
tf_bodypix/bodypix_js_utils/__init__.py
tf_bodypix/bodypix_js_utils/build_part_with_score_queue.py
tf_bodypix/bodypix_js_utils/decode_part_map.py
tf_bodypix/bodypix_js_utils/keypoints.py
tf_bodypix/bodypix_js_utils/output_rendering_util.py
tf_bodypix/bodypix_js_utils/part_channels.py
tf_bodypix/bodypix_js_utils/types.py
tf_bodypix/bodypix_js_utils/util.py
tf_bodypix/bodypix_js_utils/multi_person/__init__.py
tf_bodypix/bodypix_js_utils/multi_person/decode_multiple_poses.py
tf_bodypix/bodypix_js_utils/multi_person/decode_pose.py
tf_bodypix/bodypix_js_utils/multi_person/util.py
tf_bodypix/utils/__init__.py
tf_bodypix/utils/dist.py
tf_bodypix/utils/image.py
tf_bodypix/utils/io.py
tf_bodypix/utils/opencv.py
tf_bodypix/utils/s3.py
tf_bodypix/utils/timer.py
tf_bodypix/utils/typing.py
tf_bodypix/utils/v4l2.py
tf_bodypix-0.4.2.dist-info/LICENSE
tf_bodypix-0.4.2.dist-info/METADATA
tf_bodypix-0.4.2.dist-info/WHEEL
tf_bodypix-0.4.2.dist-info/top_level.txt
tf_bodypix-0.4.2.dist-info/RECORD
