Metadata-Version: 2.1
Name: tf-bodypix
Version: 0.4.2
Summary: Python implemention of the TensorFlow BodyPix model.
Home-page: https://github.com/de-code/python-tf-bodypix
Author: Daniel Ecer
License: UNKNOWN
Platform: UNKNOWN
Classifier: Programming Language :: Python :: 3
Classifier: License :: OSI Approved :: MIT License
Classifier: Operating System :: OS Independent
Requires-Dist: requests (>=2.26.0)
Provides-Extra: all
Requires-Dist: numpy (<1.24) ; extra == 'all'
Requires-Dist: opencv-python (==4.7.0.68) ; extra == 'all'
Requires-Dist: Pillow (==9.4.0) ; extra == 'all'
Requires-Dist: pyfakewebcam (==0.1.0) ; extra == 'all'
Requires-Dist: tensorflow (==2.11.0) ; extra == 'all'
Requires-Dist: tensorflow-estimator (==2.11.0) ; extra == 'all'
Requires-Dist: tfjs-graph-converter (==1.6.1) ; extra == 'all'
Requires-Dist: requests (>=2.26.0) ; extra == 'all'
Provides-Extra: image
Requires-Dist: Pillow (==9.4.0) ; extra == 'image'
Provides-Extra: tf
Requires-Dist: tensorflow (==2.11.0) ; extra == 'tf'
Requires-Dist: tensorflow-estimator (==2.11.0) ; extra == 'tf'
Provides-Extra: tfjs
Requires-Dist: numpy (<1.24) ; extra == 'tfjs'
Requires-Dist: tfjs-graph-converter (==1.6.1) ; extra == 'tfjs'
Provides-Extra: tflite
Requires-Dist: tflite-runtime (==2.11.0) ; extra == 'tflite'
Provides-Extra: video
Requires-Dist: opencv-python (==4.7.0.68) ; extra == 'video'
Provides-Extra: webcam
Requires-Dist: opencv-python (==4.7.0.68) ; extra == 'webcam'
Requires-Dist: pyfakewebcam (==0.1.0) ; extra == 'webcam'
